[
  {
    "question_id": "3540",
    "avg_time_to_answer": 69,
    "avg_time_to_answer_correctly": 66,
    "avg_time_to_answer_incorrectly": 38,
    "total_answered": 4784,
    "total_answered_correctly": 3177,
    "total_answered_incorrectly": 1607,
    "answers": [
      {
        "answer_id": "16069",
        "answered": 265,
        "percent_answered": 5
      },
      {
        "answer_id": "16070",
        "answered": 252,
        "percent_answered": 5
      },
      {
        "answer_id": "16071",
        "answered": 583,
        "percent_answered": 12
      },
      {
        "answer_id": "16072",
        "answered": 507,
        "percent_answered": 10
      },
      {
        "answer_id": "16073",
        "answered": 3177,
        "percent_answered": 66
      }
    ],
    "timings": [
      {
        "seconds_passed": 0,
        "total_answered": 33,
        "total_answered_correctly": 18
      },
      {
        "seconds_passed": 5,
        "total_answered": 117,
        "total_answered_correctly": 91
      },
      {
        "seconds_passed": 10,
        "total_answered": 161,
        "total_answered_correctly": 119
      },
      {
        "seconds_passed": 15,
        "total_answered": 222,
        "total_answered_correctly": 162
      },
      {
        "seconds_passed": 20,
        "total_answered": 304,
        "total_answered_correctly": 227
      },
      {
        "seconds_passed": 25,
        "total_answered": 434,
        "total_answered_correctly": 318
      },
      {
        "seconds_passed": 30,
        "total_answered": 613,
        "total_answered_correctly": 453
      },
      {
        "seconds_passed": 35,
        "total_answered": 875,
        "total_answered_correctly": 649
      },
      {
        "seconds_passed": 40,
        "total_answered": 1145,
        "total_answered_correctly": 838
      },
      {
        "seconds_passed": 45,
        "total_answered": 1410,
        "total_answered_correctly": 1037
      },
      {
        "seconds_passed": 50,
        "total_answered": 1703,
        "total_answered_correctly": 1252
      },
      {
        "seconds_passed": 55,
        "total_answered": 1984,
        "total_answered_correctly": 1443
      },
      {
        "seconds_passed": 60,
        "total_answered": 2265,
        "total_answered_correctly": 1643
      },
      {
        "seconds_passed": 65,
        "total_answered": 2520,
        "total_answered_correctly": 1831
      },
      {
        "seconds_passed": 70,
        "total_answered": 2792,
        "total_answered_correctly": 2002
      },
      {
        "seconds_passed": 75,
        "total_answered": 3043,
        "total_answered_correctly": 2162
      },
      {
        "seconds_passed": 80,
        "total_answered": 3279,
        "total_answered_correctly": 2311
      },
      {
        "seconds_passed": 85,
        "total_answered": 3535,
        "total_answered_correctly": 2469
      },
      {
        "seconds_passed": 90,
        "total_answered": 3749,
        "total_answered_correctly": 2598
      },
      {
        "seconds_passed": 95,
        "total_answered": 3921,
        "total_answered_correctly": 2707
      },
      {
        "seconds_passed": 100,
        "total_answered": 4099,
        "total_answered_correctly": 2804
      },
      {
        "seconds_passed": 105,
        "total_answered": 4266,
        "total_answered_correctly": 2892
      },
      {
        "seconds_passed": 110,
        "total_answered": 4416,
        "total_answered_correctly": 2976
      },
      {
        "seconds_passed": 115,
        "total_answered": 4576,
        "total_answered_correctly": 3050
      },
      {
        "seconds_passed": 120,
        "total_answered": 4637,
        "total_answered_correctly": 3081
      },
      {
        "seconds_passed": 125,
        "total_answered": 4661,
        "total_answered_correctly": 3096
      },
      {
        "seconds_passed": 130,
        "total_answered": 4674,
        "total_answered_correctly": 3103
      },
      {
        "seconds_passed": 135,
        "total_answered": 4681,
        "total_answered_correctly": 3108
      },
      {
        "seconds_passed": 140,
        "total_answered": 4692,
        "total_answered_correctly": 3115
      },
      {
        "seconds_passed": 145,
        "total_answered": 4706,
        "total_answered_correctly": 3125
      },
      {
        "seconds_passed": 150,
        "total_answered": 4712,
        "total_answered_correctly": 3130
      },
      {
        "seconds_passed": 155,
        "total_answered": 4714,
        "total_answered_correctly": 3131
      },
      {
        "seconds_passed": 160,
        "total_answered": 4722,
        "total_answered_correctly": 3137
      },
      {
        "seconds_passed": 165,
        "total_answered": 4725,
        "total_answered_correctly": 3139
      },
      {
        "seconds_passed": 170,
        "total_answered": 4731,
        "total_answered_correctly": 3143
      },
      {
        "seconds_passed": 175,
        "total_answered": 4732,
        "total_answered_correctly": 3144
      },
      {
        "seconds_passed": 180,
        "total_answered": 4736,
        "total_answered_correctly": 3147
      },
      {
        "seconds_passed": 185,
        "total_answered": 4741,
        "total_answered_correctly": 3150
      },
      {
        "seconds_passed": 190,
        "total_answered": 4745,
        "total_answered_correctly": 3151
      },
      {
        "seconds_passed": 195,
        "total_answered": 4749,
        "total_answered_correctly": 3154
      },
      {
        "seconds_passed": 200,
        "total_answered": 4752,
        "total_answered_correctly": 3155
      }
    ]
  }
]