[
  {
    "question_id": "3895",
    "avg_time_to_answer": 47,
    "avg_time_to_answer_correctly": 42,
    "avg_time_to_answer_incorrectly": 27,
    "total_answered": 7952,
    "total_answered_correctly": 5326,
    "total_answered_incorrectly": 2626,
    "answers": [
      {
        "answer_id": "17844",
        "answered": 354,
        "percent_answered": 4
      },
      {
        "answer_id": "17845",
        "answered": 452,
        "percent_answered": 5
      },
      {
        "answer_id": "17846",
        "answered": 1360,
        "percent_answered": 17
      },
      {
        "answer_id": "17847",
        "answered": 5326,
        "percent_answered": 67
      },
      {
        "answer_id": "17848",
        "answered": 460,
        "percent_answered": 5
      }
    ],
    "timings": [
      {
        "seconds_passed": 0,
        "total_answered": 13,
        "total_answered_correctly": 4
      },
      {
        "seconds_passed": 5,
        "total_answered": 202,
        "total_answered_correctly": 178
      },
      {
        "seconds_passed": 10,
        "total_answered": 496,
        "total_answered_correctly": 433
      },
      {
        "seconds_passed": 15,
        "total_answered": 930,
        "total_answered_correctly": 814
      },
      {
        "seconds_passed": 20,
        "total_answered": 1477,
        "total_answered_correctly": 1248
      },
      {
        "seconds_passed": 25,
        "total_answered": 2125,
        "total_answered_correctly": 1755
      },
      {
        "seconds_passed": 30,
        "total_answered": 2815,
        "total_answered_correctly": 2263
      },
      {
        "seconds_passed": 35,
        "total_answered": 3489,
        "total_answered_correctly": 2734
      },
      {
        "seconds_passed": 40,
        "total_answered": 4107,
        "total_answered_correctly": 3148
      },
      {
        "seconds_passed": 45,
        "total_answered": 4716,
        "total_answered_correctly": 3509
      },
      {
        "seconds_passed": 50,
        "total_answered": 5223,
        "total_answered_correctly": 3817
      },
      {
        "seconds_passed": 55,
        "total_answered": 5683,
        "total_answered_correctly": 4092
      },
      {
        "seconds_passed": 60,
        "total_answered": 6073,
        "total_answered_correctly": 4317
      },
      {
        "seconds_passed": 65,
        "total_answered": 6394,
        "total_answered_correctly": 4505
      },
      {
        "seconds_passed": 70,
        "total_answered": 6660,
        "total_answered_correctly": 4652
      },
      {
        "seconds_passed": 75,
        "total_answered": 6876,
        "total_answered_correctly": 4774
      },
      {
        "seconds_passed": 80,
        "total_answered": 7100,
        "total_answered_correctly": 4897
      },
      {
        "seconds_passed": 85,
        "total_answered": 7269,
        "total_answered_correctly": 4980
      },
      {
        "seconds_passed": 90,
        "total_answered": 7416,
        "total_answered_correctly": 5056
      },
      {
        "seconds_passed": 95,
        "total_answered": 7529,
        "total_answered_correctly": 5114
      },
      {
        "seconds_passed": 100,
        "total_answered": 7630,
        "total_answered_correctly": 5170
      },
      {
        "seconds_passed": 105,
        "total_answered": 7733,
        "total_answered_correctly": 5215
      },
      {
        "seconds_passed": 110,
        "total_answered": 7803,
        "total_answered_correctly": 5253
      },
      {
        "seconds_passed": 115,
        "total_answered": 7863,
        "total_answered_correctly": 5283
      },
      {
        "seconds_passed": 120,
        "total_answered": 7888,
        "total_answered_correctly": 5296
      },
      {
        "seconds_passed": 125,
        "total_answered": 7895,
        "total_answered_correctly": 5300
      },
      {
        "seconds_passed": 130,
        "total_answered": 7900,
        "total_answered_correctly": 5303
      },
      {
        "seconds_passed": 135,
        "total_answered": 7904,
        "total_answered_correctly": 5304
      },
      {
        "seconds_passed": 140,
        "total_answered": 7908,
        "total_answered_correctly": 5306
      },
      {
        "seconds_passed": 145,
        "total_answered": 7909,
        "total_answered_correctly": 5306
      },
      {
        "seconds_passed": 150,
        "total_answered": 7911,
        "total_answered_correctly": 5307
      },
      {
        "seconds_passed": 155,
        "total_answered": 7915,
        "total_answered_correctly": 5309
      },
      {
        "seconds_passed": 160,
        "total_answered": 7916,
        "total_answered_correctly": 5309
      },
      {
        "seconds_passed": 165,
        "total_answered": 7918,
        "total_answered_correctly": 5311
      },
      {
        "seconds_passed": 170,
        "total_answered": 7919,
        "total_answered_correctly": 5312
      },
      {
        "seconds_passed": 175,
        "total_answered": 7921,
        "total_answered_correctly": 5313
      },
      {
        "seconds_passed": 180,
        "total_answered": 7925,
        "total_answered_correctly": 5314
      },
      {
        "seconds_passed": 185,
        "total_answered": 7927,
        "total_answered_correctly": 5314
      },
      {
        "seconds_passed": 190,
        "total_answered": 7928,
        "total_answered_correctly": 5315
      },
      {
        "seconds_passed": 195,
        "total_answered": 7929,
        "total_answered_correctly": 5315
      },
      {
        "seconds_passed": 200,
        "total_answered": 7931,
        "total_answered_correctly": 5315
      }
    ]
  }
]