[
  {
    "question_id": "b61513fa-0dbf-64be-c927-6fb37800c266",
    "avg_time_to_answer": 60,
    "avg_time_to_answer_correctly": 35,
    "avg_time_to_answer_incorrectly": 231,
    "total_answered": 758,
    "total_answered_correctly": 170,
    "total_answered_incorrectly": 588,
    "answers": [
      {
        "answer_id": "7f021a0e-7401-0e93-1c70-39a42d8b1f68",
        "answered": 150,
        "percent_answered": 20
      },
      {
        "answer_id": "8e169467-2d5a-796f-ab97-b73f5d16052e",
        "answered": 339,
        "percent_answered": 46
      },
      {
        "answer_id": "6351bf1c-3be9-b06e-0863-a56a0be08e4d",
        "answered": 266,
        "percent_answered": 36
      }
    ],
    "timings": [
      {
        "seconds_passed": 0,
        "total_answered": 20,
        "total_answered_correctly": 6
      },
      {
        "seconds_passed": 5,
        "total_answered": 128,
        "total_answered_correctly": 45
      },
      {
        "seconds_passed": 10,
        "total_answered": 199,
        "total_answered_correctly": 84
      },
      {
        "seconds_passed": 15,
        "total_answered": 258,
        "total_answered_correctly": 101
      },
      {
        "seconds_passed": 20,
        "total_answered": 291,
        "total_answered_correctly": 110
      },
      {
        "seconds_passed": 25,
        "total_answered": 319,
        "total_answered_correctly": 119
      },
      {
        "seconds_passed": 30,
        "total_answered": 345,
        "total_answered_correctly": 123
      },
      {
        "seconds_passed": 35,
        "total_answered": 379,
        "total_answered_correctly": 131
      },
      {
        "seconds_passed": 40,
        "total_answered": 403,
        "total_answered_correctly": 132
      },
      {
        "seconds_passed": 45,
        "total_answered": 427,
        "total_answered_correctly": 134
      },
      {
        "seconds_passed": 50,
        "total_answered": 448,
        "total_answered_correctly": 137
      },
      {
        "seconds_passed": 55,
        "total_answered": 466,
        "total_answered_correctly": 138
      },
      {
        "seconds_passed": 60,
        "total_answered": 489,
        "total_answered_correctly": 138
      },
      {
        "seconds_passed": 65,
        "total_answered": 520,
        "total_answered_correctly": 139
      },
      {
        "seconds_passed": 70,
        "total_answered": 544,
        "total_answered_correctly": 141
      },
      {
        "seconds_passed": 75,
        "total_answered": 561,
        "total_answered_correctly": 143
      },
      {
        "seconds_passed": 80,
        "total_answered": 580,
        "total_answered_correctly": 146
      },
      {
        "seconds_passed": 85,
        "total_answered": 588,
        "total_answered_correctly": 146
      },
      {
        "seconds_passed": 90,
        "total_answered": 607,
        "total_answered_correctly": 147
      },
      {
        "seconds_passed": 95,
        "total_answered": 624,
        "total_answered_correctly": 148
      },
      {
        "seconds_passed": 100,
        "total_answered": 640,
        "total_answered_correctly": 150
      },
      {
        "seconds_passed": 105,
        "total_answered": 650,
        "total_answered_correctly": 153
      },
      {
        "seconds_passed": 110,
        "total_answered": 661,
        "total_answered_correctly": 155
      },
      {
        "seconds_passed": 115,
        "total_answered": 673,
        "total_answered_correctly": 157
      },
      {
        "seconds_passed": 120,
        "total_answered": 682,
        "total_answered_correctly": 158
      },
      {
        "seconds_passed": 125,
        "total_answered": 688,
        "total_answered_correctly": 158
      },
      {
        "seconds_passed": 130,
        "total_answered": 698,
        "total_answered_correctly": 159
      },
      {
        "seconds_passed": 135,
        "total_answered": 702,
        "total_answered_correctly": 160
      },
      {
        "seconds_passed": 140,
        "total_answered": 704,
        "total_answered_correctly": 160
      },
      {
        "seconds_passed": 145,
        "total_answered": 710,
        "total_answered_correctly": 161
      },
      {
        "seconds_passed": 150,
        "total_answered": 711,
        "total_answered_correctly": 161
      },
      {
        "seconds_passed": 155,
        "total_answered": 715,
        "total_answered_correctly": 161
      },
      {
        "seconds_passed": 160,
        "total_answered": 720,
        "total_answered_correctly": 162
      },
      {
        "seconds_passed": 170,
        "total_answered": 723,
        "total_answered_correctly": 163
      },
      {
        "seconds_passed": 175,
        "total_answered": 724,
        "total_answered_correctly": 163
      },
      {
        "seconds_passed": 185,
        "total_answered": 728,
        "total_answered_correctly": 165
      },
      {
        "seconds_passed": 190,
        "total_answered": 729,
        "total_answered_correctly": 166
      },
      {
        "seconds_passed": 195,
        "total_answered": 730,
        "total_answered_correctly": 166
      },
      {
        "seconds_passed": 200,
        "total_answered": 732,
        "total_answered_correctly": 166
      }
    ]
  }
]