[
  {
    "question_id": "124d2c23-b382-c5a8-8b49-8e939028c91b",
    "avg_time_to_answer": 61,
    "avg_time_to_answer_correctly": 48,
    "avg_time_to_answer_incorrectly": 44,
    "total_answered": 3955,
    "total_answered_correctly": 2625,
    "total_answered_incorrectly": 1330,
    "answers": [
      {
        "answer_id": "f8cc0cbf-a02d-446c-5d7a-aad6ae110335",
        "answered": 2623,
        "percent_answered": 68
      },
      {
        "answer_id": "66b17ebe-acee-1904-5080-f2d5e114ec53",
        "answered": 415,
        "percent_answered": 10
      },
      {
        "answer_id": "5df68537-78e0-2128-7fdc-f5c87b626991",
        "answered": 316,
        "percent_answered": 8
      },
      {
        "answer_id": "8da49ce3-f347-5517-c36c-dadb9f5b94c5",
        "answered": 383,
        "percent_answered": 9
      },
      {
        "answer_id": "1c5e17eb-c11e-c6fe-a64b-a64c6d6154bc",
        "answered": 218,
        "percent_answered": 5
      }
    ],
    "timings": [
      {
        "seconds_passed": 0,
        "total_answered": 98,
        "total_answered_correctly": 19
      },
      {
        "seconds_passed": 5,
        "total_answered": 230,
        "total_answered_correctly": 76
      },
      {
        "seconds_passed": 10,
        "total_answered": 272,
        "total_answered_correctly": 95
      },
      {
        "seconds_passed": 15,
        "total_answered": 300,
        "total_answered_correctly": 105
      },
      {
        "seconds_passed": 20,
        "total_answered": 331,
        "total_answered_correctly": 124
      },
      {
        "seconds_passed": 25,
        "total_answered": 385,
        "total_answered_correctly": 156
      },
      {
        "seconds_passed": 30,
        "total_answered": 496,
        "total_answered_correctly": 242
      },
      {
        "seconds_passed": 35,
        "total_answered": 636,
        "total_answered_correctly": 352
      },
      {
        "seconds_passed": 40,
        "total_answered": 832,
        "total_answered_correctly": 514
      },
      {
        "seconds_passed": 45,
        "total_answered": 1049,
        "total_answered_correctly": 702
      },
      {
        "seconds_passed": 50,
        "total_answered": 1291,
        "total_answered_correctly": 882
      },
      {
        "seconds_passed": 55,
        "total_answered": 1510,
        "total_answered_correctly": 1064
      },
      {
        "seconds_passed": 60,
        "total_answered": 1767,
        "total_answered_correctly": 1277
      },
      {
        "seconds_passed": 65,
        "total_answered": 1977,
        "total_answered_correctly": 1446
      },
      {
        "seconds_passed": 70,
        "total_answered": 2169,
        "total_answered_correctly": 1595
      },
      {
        "seconds_passed": 75,
        "total_answered": 2333,
        "total_answered_correctly": 1718
      },
      {
        "seconds_passed": 80,
        "total_answered": 2518,
        "total_answered_correctly": 1855
      },
      {
        "seconds_passed": 85,
        "total_answered": 2646,
        "total_answered_correctly": 1941
      },
      {
        "seconds_passed": 90,
        "total_answered": 2795,
        "total_answered_correctly": 2039
      },
      {
        "seconds_passed": 95,
        "total_answered": 2910,
        "total_answered_correctly": 2116
      },
      {
        "seconds_passed": 100,
        "total_answered": 3003,
        "total_answered_correctly": 2173
      },
      {
        "seconds_passed": 105,
        "total_answered": 3108,
        "total_answered_correctly": 2239
      },
      {
        "seconds_passed": 110,
        "total_answered": 3202,
        "total_answered_correctly": 2299
      },
      {
        "seconds_passed": 115,
        "total_answered": 3282,
        "total_answered_correctly": 2346
      },
      {
        "seconds_passed": 120,
        "total_answered": 3360,
        "total_answered_correctly": 2386
      },
      {
        "seconds_passed": 125,
        "total_answered": 3439,
        "total_answered_correctly": 2413
      },
      {
        "seconds_passed": 130,
        "total_answered": 3517,
        "total_answered_correctly": 2446
      },
      {
        "seconds_passed": 135,
        "total_answered": 3590,
        "total_answered_correctly": 2477
      },
      {
        "seconds_passed": 140,
        "total_answered": 3646,
        "total_answered_correctly": 2495
      },
      {
        "seconds_passed": 145,
        "total_answered": 3715,
        "total_answered_correctly": 2519
      },
      {
        "seconds_passed": 150,
        "total_answered": 3756,
        "total_answered_correctly": 2534
      },
      {
        "seconds_passed": 155,
        "total_answered": 3771,
        "total_answered_correctly": 2539
      },
      {
        "seconds_passed": 160,
        "total_answered": 3789,
        "total_answered_correctly": 2549
      },
      {
        "seconds_passed": 165,
        "total_answered": 3802,
        "total_answered_correctly": 2556
      },
      {
        "seconds_passed": 170,
        "total_answered": 3809,
        "total_answered_correctly": 2557
      },
      {
        "seconds_passed": 175,
        "total_answered": 3820,
        "total_answered_correctly": 2563
      },
      {
        "seconds_passed": 180,
        "total_answered": 3830,
        "total_answered_correctly": 2567
      },
      {
        "seconds_passed": 185,
        "total_answered": 3837,
        "total_answered_correctly": 2569
      },
      {
        "seconds_passed": 190,
        "total_answered": 3841,
        "total_answered_correctly": 2572
      },
      {
        "seconds_passed": 195,
        "total_answered": 3847,
        "total_answered_correctly": 2576
      },
      {
        "seconds_passed": 200,
        "total_answered": 3855,
        "total_answered_correctly": 2578
      }
    ]
  }
]