[
  {
    "question_id": "4213",
    "avg_time_to_answer": 117,
    "avg_time_to_answer_correctly": 116,
    "avg_time_to_answer_incorrectly": 70,
    "total_answered": 3126,
    "total_answered_correctly": 1958,
    "total_answered_incorrectly": 1168,
    "answers": [
      {
        "answer_id": "19434",
        "answered": 142,
        "percent_answered": 4
      },
      {
        "answer_id": "19435",
        "answered": 261,
        "percent_answered": 8
      },
      {
        "answer_id": "19436",
        "answered": 262,
        "percent_answered": 8
      },
      {
        "answer_id": "19437",
        "answered": 503,
        "percent_answered": 17
      },
      {
        "answer_id": "19438",
        "answered": 1958,
        "percent_answered": 66
      }
    ],
    "timings": [
      {
        "seconds_passed": 0,
        "total_answered": 34,
        "total_answered_correctly": 5
      },
      {
        "seconds_passed": 5,
        "total_answered": 149,
        "total_answered_correctly": 80
      },
      {
        "seconds_passed": 10,
        "total_answered": 206,
        "total_answered_correctly": 113
      },
      {
        "seconds_passed": 15,
        "total_answered": 231,
        "total_answered_correctly": 125
      },
      {
        "seconds_passed": 20,
        "total_answered": 263,
        "total_answered_correctly": 140
      },
      {
        "seconds_passed": 25,
        "total_answered": 285,
        "total_answered_correctly": 148
      },
      {
        "seconds_passed": 30,
        "total_answered": 311,
        "total_answered_correctly": 160
      },
      {
        "seconds_passed": 35,
        "total_answered": 326,
        "total_answered_correctly": 168
      },
      {
        "seconds_passed": 40,
        "total_answered": 359,
        "total_answered_correctly": 182
      },
      {
        "seconds_passed": 45,
        "total_answered": 391,
        "total_answered_correctly": 198
      },
      {
        "seconds_passed": 50,
        "total_answered": 429,
        "total_answered_correctly": 221
      },
      {
        "seconds_passed": 55,
        "total_answered": 477,
        "total_answered_correctly": 251
      },
      {
        "seconds_passed": 60,
        "total_answered": 551,
        "total_answered_correctly": 302
      },
      {
        "seconds_passed": 65,
        "total_answered": 636,
        "total_answered_correctly": 357
      },
      {
        "seconds_passed": 70,
        "total_answered": 724,
        "total_answered_correctly": 421
      },
      {
        "seconds_passed": 75,
        "total_answered": 822,
        "total_answered_correctly": 494
      },
      {
        "seconds_passed": 80,
        "total_answered": 932,
        "total_answered_correctly": 571
      },
      {
        "seconds_passed": 85,
        "total_answered": 1031,
        "total_answered_correctly": 644
      },
      {
        "seconds_passed": 90,
        "total_answered": 1142,
        "total_answered_correctly": 715
      },
      {
        "seconds_passed": 95,
        "total_answered": 1273,
        "total_answered_correctly": 805
      },
      {
        "seconds_passed": 100,
        "total_answered": 1397,
        "total_answered_correctly": 890
      },
      {
        "seconds_passed": 105,
        "total_answered": 1515,
        "total_answered_correctly": 971
      },
      {
        "seconds_passed": 110,
        "total_answered": 1636,
        "total_answered_correctly": 1055
      },
      {
        "seconds_passed": 115,
        "total_answered": 1771,
        "total_answered_correctly": 1141
      },
      {
        "seconds_passed": 120,
        "total_answered": 1901,
        "total_answered_correctly": 1229
      },
      {
        "seconds_passed": 125,
        "total_answered": 2043,
        "total_answered_correctly": 1319
      },
      {
        "seconds_passed": 130,
        "total_answered": 2192,
        "total_answered_correctly": 1410
      },
      {
        "seconds_passed": 135,
        "total_answered": 2318,
        "total_answered_correctly": 1481
      },
      {
        "seconds_passed": 140,
        "total_answered": 2483,
        "total_answered_correctly": 1575
      },
      {
        "seconds_passed": 145,
        "total_answered": 2671,
        "total_answered_correctly": 1678
      },
      {
        "seconds_passed": 150,
        "total_answered": 2749,
        "total_answered_correctly": 1717
      },
      {
        "seconds_passed": 155,
        "total_answered": 2773,
        "total_answered_correctly": 1731
      },
      {
        "seconds_passed": 160,
        "total_answered": 2789,
        "total_answered_correctly": 1742
      },
      {
        "seconds_passed": 165,
        "total_answered": 2805,
        "total_answered_correctly": 1756
      },
      {
        "seconds_passed": 170,
        "total_answered": 2824,
        "total_answered_correctly": 1767
      },
      {
        "seconds_passed": 175,
        "total_answered": 2845,
        "total_answered_correctly": 1779
      },
      {
        "seconds_passed": 180,
        "total_answered": 2855,
        "total_answered_correctly": 1788
      },
      {
        "seconds_passed": 185,
        "total_answered": 2875,
        "total_answered_correctly": 1798
      },
      {
        "seconds_passed": 190,
        "total_answered": 2893,
        "total_answered_correctly": 1808
      },
      {
        "seconds_passed": 195,
        "total_answered": 2908,
        "total_answered_correctly": 1818
      },
      {
        "seconds_passed": 200,
        "total_answered": 2924,
        "total_answered_correctly": 1828
      }
    ]
  }
]