[
  {
    "question_id": "2a5ed7c0-9756-012d-6082-123139068df2",
    "avg_time_to_answer": 52,
    "avg_time_to_answer_correctly": 49,
    "avg_time_to_answer_incorrectly": 53,
    "total_answered": 203,
    "total_answered_correctly": 104,
    "total_answered_incorrectly": 99,
    "answers": [
      {
        "answer_id": "2a638320-9756-012d-6082-123139068df2",
        "answered": 40,
        "percent_answered": 19
      },
      {
        "answer_id": "2a64f9f0-9756-012d-6082-123139068df2",
        "answered": 104,
        "percent_answered": 51
      },
      {
        "answer_id": "2a664690-9756-012d-6082-123139068df2",
        "answered": 51,
        "percent_answered": 25
      },
      {
        "answer_id": "2a67aac0-9756-012d-6082-123139068df2",
        "answered": 8,
        "percent_answered": 3
      }
    ],
    "timings": [
      {
        "seconds_passed": 0,
        "total_answered": 9,
        "total_answered_correctly": 3
      },
      {
        "seconds_passed": 5,
        "total_answered": 23,
        "total_answered_correctly": 8
      },
      {
        "seconds_passed": 10,
        "total_answered": 31,
        "total_answered_correctly": 13
      },
      {
        "seconds_passed": 15,
        "total_answered": 35,
        "total_answered_correctly": 16
      },
      {
        "seconds_passed": 20,
        "total_answered": 54,
        "total_answered_correctly": 28
      },
      {
        "seconds_passed": 25,
        "total_answered": 63,
        "total_answered_correctly": 35
      },
      {
        "seconds_passed": 30,
        "total_answered": 75,
        "total_answered_correctly": 44
      },
      {
        "seconds_passed": 35,
        "total_answered": 85,
        "total_answered_correctly": 47
      },
      {
        "seconds_passed": 40,
        "total_answered": 100,
        "total_answered_correctly": 58
      },
      {
        "seconds_passed": 45,
        "total_answered": 113,
        "total_answered_correctly": 63
      },
      {
        "seconds_passed": 50,
        "total_answered": 124,
        "total_answered_correctly": 69
      },
      {
        "seconds_passed": 55,
        "total_answered": 133,
        "total_answered_correctly": 75
      },
      {
        "seconds_passed": 60,
        "total_answered": 140,
        "total_answered_correctly": 77
      },
      {
        "seconds_passed": 65,
        "total_answered": 147,
        "total_answered_correctly": 80
      },
      {
        "seconds_passed": 70,
        "total_answered": 154,
        "total_answered_correctly": 81
      },
      {
        "seconds_passed": 75,
        "total_answered": 161,
        "total_answered_correctly": 85
      },
      {
        "seconds_passed": 80,
        "total_answered": 166,
        "total_answered_correctly": 87
      },
      {
        "seconds_passed": 85,
        "total_answered": 173,
        "total_answered_correctly": 90
      },
      {
        "seconds_passed": 90,
        "total_answered": 176,
        "total_answered_correctly": 91
      },
      {
        "seconds_passed": 95,
        "total_answered": 179,
        "total_answered_correctly": 93
      },
      {
        "seconds_passed": 100,
        "total_answered": 184,
        "total_answered_correctly": 94
      },
      {
        "seconds_passed": 105,
        "total_answered": 187,
        "total_answered_correctly": 95
      },
      {
        "seconds_passed": 110,
        "total_answered": 188,
        "total_answered_correctly": 96
      },
      {
        "seconds_passed": 120,
        "total_answered": 190,
        "total_answered_correctly": 98
      },
      {
        "seconds_passed": 135,
        "total_answered": 191,
        "total_answered_correctly": 98
      },
      {
        "seconds_passed": 140,
        "total_answered": 192,
        "total_answered_correctly": 99
      },
      {
        "seconds_passed": 145,
        "total_answered": 193,
        "total_answered_correctly": 100
      },
      {
        "seconds_passed": 150,
        "total_answered": 196,
        "total_answered_correctly": 101
      },
      {
        "seconds_passed": 160,
        "total_answered": 198,
        "total_answered_correctly": 102
      },
      {
        "seconds_passed": 170,
        "total_answered": 199,
        "total_answered_correctly": 103
      },
      {
        "seconds_passed": 175,
        "total_answered": 200,
        "total_answered_correctly": 103
      },
      {
        "seconds_passed": 180,
        "total_answered": 201,
        "total_answered_correctly": 104
      }
    ]
  }
]