[
  {
    "question_id": "1561",
    "avg_time_to_answer": 78,
    "avg_time_to_answer_correctly": 56,
    "avg_time_to_answer_incorrectly": 147,
    "total_answered": 6579,
    "total_answered_correctly": 2527,
    "total_answered_incorrectly": 4052,
    "answers": [
      {
        "answer_id": "a48eb6d8-30a6-1c8b-2814-053d09f94103",
        "answered": 0,
        "percent_answered": 0
      }
    ],
    "timings": [
      {
        "seconds_passed": 0,
        "total_answered": 256,
        "total_answered_correctly": 233
      },
      {
        "seconds_passed": 5,
        "total_answered": 862,
        "total_answered_correctly": 702
      },
      {
        "seconds_passed": 10,
        "total_answered": 1231,
        "total_answered_correctly": 958
      },
      {
        "seconds_passed": 15,
        "total_answered": 1471,
        "total_answered_correctly": 1081
      },
      {
        "seconds_passed": 20,
        "total_answered": 1651,
        "total_answered_correctly": 1151
      },
      {
        "seconds_passed": 25,
        "total_answered": 1851,
        "total_answered_correctly": 1220
      },
      {
        "seconds_passed": 30,
        "total_answered": 2015,
        "total_answered_correctly": 1278
      },
      {
        "seconds_passed": 35,
        "total_answered": 2222,
        "total_answered_correctly": 1337
      },
      {
        "seconds_passed": 40,
        "total_answered": 2401,
        "total_answered_correctly": 1384
      },
      {
        "seconds_passed": 45,
        "total_answered": 2602,
        "total_answered_correctly": 1438
      },
      {
        "seconds_passed": 50,
        "total_answered": 2852,
        "total_answered_correctly": 1503
      },
      {
        "seconds_passed": 55,
        "total_answered": 3073,
        "total_answered_correctly": 1551
      },
      {
        "seconds_passed": 60,
        "total_answered": 3278,
        "total_answered_correctly": 1614
      },
      {
        "seconds_passed": 65,
        "total_answered": 3519,
        "total_answered_correctly": 1682
      },
      {
        "seconds_passed": 70,
        "total_answered": 3771,
        "total_answered_correctly": 1757
      },
      {
        "seconds_passed": 75,
        "total_answered": 3967,
        "total_answered_correctly": 1804
      },
      {
        "seconds_passed": 80,
        "total_answered": 4142,
        "total_answered_correctly": 1852
      },
      {
        "seconds_passed": 85,
        "total_answered": 4350,
        "total_answered_correctly": 1905
      },
      {
        "seconds_passed": 90,
        "total_answered": 4500,
        "total_answered_correctly": 1955
      },
      {
        "seconds_passed": 95,
        "total_answered": 4683,
        "total_answered_correctly": 2011
      },
      {
        "seconds_passed": 100,
        "total_answered": 4829,
        "total_answered_correctly": 2062
      },
      {
        "seconds_passed": 105,
        "total_answered": 4979,
        "total_answered_correctly": 2103
      },
      {
        "seconds_passed": 110,
        "total_answered": 5102,
        "total_answered_correctly": 2151
      },
      {
        "seconds_passed": 115,
        "total_answered": 5206,
        "total_answered_correctly": 2173
      },
      {
        "seconds_passed": 120,
        "total_answered": 5312,
        "total_answered_correctly": 2204
      },
      {
        "seconds_passed": 125,
        "total_answered": 5394,
        "total_answered_correctly": 2228
      },
      {
        "seconds_passed": 130,
        "total_answered": 5490,
        "total_answered_correctly": 2249
      },
      {
        "seconds_passed": 135,
        "total_answered": 5573,
        "total_answered_correctly": 2268
      },
      {
        "seconds_passed": 140,
        "total_answered": 5648,
        "total_answered_correctly": 2293
      },
      {
        "seconds_passed": 145,
        "total_answered": 5724,
        "total_answered_correctly": 2307
      },
      {
        "seconds_passed": 150,
        "total_answered": 5799,
        "total_answered_correctly": 2322
      },
      {
        "seconds_passed": 155,
        "total_answered": 5863,
        "total_answered_correctly": 2340
      },
      {
        "seconds_passed": 160,
        "total_answered": 5910,
        "total_answered_correctly": 2354
      },
      {
        "seconds_passed": 165,
        "total_answered": 5967,
        "total_answered_correctly": 2372
      },
      {
        "seconds_passed": 170,
        "total_answered": 6025,
        "total_answered_correctly": 2390
      },
      {
        "seconds_passed": 175,
        "total_answered": 6080,
        "total_answered_correctly": 2412
      },
      {
        "seconds_passed": 180,
        "total_answered": 6125,
        "total_answered_correctly": 2426
      },
      {
        "seconds_passed": 185,
        "total_answered": 6168,
        "total_answered_correctly": 2432
      },
      {
        "seconds_passed": 190,
        "total_answered": 6202,
        "total_answered_correctly": 2440
      },
      {
        "seconds_passed": 195,
        "total_answered": 6241,
        "total_answered_correctly": 2450
      },
      {
        "seconds_passed": 200,
        "total_answered": 6283,
        "total_answered_correctly": 2460
      }
    ]
  }
]