[
  {
    "question_id": "852cc94b-ffdd-70b5-5dac-8f743f88449a",
    "avg_time_to_answer": 97,
    "avg_time_to_answer_correctly": 107,
    "avg_time_to_answer_incorrectly": 159,
    "total_answered": 1108,
    "total_answered_correctly": 401,
    "total_answered_incorrectly": 707,
    "answers": [
      {
        "answer_id": "23bfbaaf-0a99-aa96-4ebe-abd7b22c7a06",
        "answered": 689,
        "percent_answered": 68
      },
      {
        "answer_id": "7e10776f-c8a3-ff80-3c07-62a1c4d77f92",
        "answered": 108,
        "percent_answered": 10
      },
      {
        "answer_id": "1914406a-1a29-b041-b1f5-bf5796c5c8e4",
        "answered": 80,
        "percent_answered": 7
      },
      {
        "answer_id": "c3cc5e44-20da-4dba-593b-d7e3fc2161cd",
        "answered": 222,
        "percent_answered": 21
      }
    ],
    "timings": [
      {
        "seconds_passed": 0,
        "total_answered": 6,
        "total_answered_correctly": 2
      },
      {
        "seconds_passed": 5,
        "total_answered": 45,
        "total_answered_correctly": 10
      },
      {
        "seconds_passed": 10,
        "total_answered": 75,
        "total_answered_correctly": 13
      },
      {
        "seconds_passed": 15,
        "total_answered": 104,
        "total_answered_correctly": 23
      },
      {
        "seconds_passed": 20,
        "total_answered": 135,
        "total_answered_correctly": 33
      },
      {
        "seconds_passed": 25,
        "total_answered": 176,
        "total_answered_correctly": 45
      },
      {
        "seconds_passed": 30,
        "total_answered": 224,
        "total_answered_correctly": 61
      },
      {
        "seconds_passed": 35,
        "total_answered": 273,
        "total_answered_correctly": 83
      },
      {
        "seconds_passed": 40,
        "total_answered": 315,
        "total_answered_correctly": 99
      },
      {
        "seconds_passed": 45,
        "total_answered": 370,
        "total_answered_correctly": 119
      },
      {
        "seconds_passed": 50,
        "total_answered": 418,
        "total_answered_correctly": 136
      },
      {
        "seconds_passed": 55,
        "total_answered": 471,
        "total_answered_correctly": 153
      },
      {
        "seconds_passed": 60,
        "total_answered": 511,
        "total_answered_correctly": 166
      },
      {
        "seconds_passed": 65,
        "total_answered": 546,
        "total_answered_correctly": 179
      },
      {
        "seconds_passed": 70,
        "total_answered": 589,
        "total_answered_correctly": 190
      },
      {
        "seconds_passed": 75,
        "total_answered": 613,
        "total_answered_correctly": 200
      },
      {
        "seconds_passed": 80,
        "total_answered": 645,
        "total_answered_correctly": 211
      },
      {
        "seconds_passed": 85,
        "total_answered": 677,
        "total_answered_correctly": 225
      },
      {
        "seconds_passed": 90,
        "total_answered": 709,
        "total_answered_correctly": 237
      },
      {
        "seconds_passed": 95,
        "total_answered": 746,
        "total_answered_correctly": 256
      },
      {
        "seconds_passed": 100,
        "total_answered": 765,
        "total_answered_correctly": 267
      },
      {
        "seconds_passed": 105,
        "total_answered": 800,
        "total_answered_correctly": 281
      },
      {
        "seconds_passed": 110,
        "total_answered": 822,
        "total_answered_correctly": 287
      },
      {
        "seconds_passed": 115,
        "total_answered": 838,
        "total_answered_correctly": 296
      },
      {
        "seconds_passed": 120,
        "total_answered": 855,
        "total_answered_correctly": 303
      },
      {
        "seconds_passed": 125,
        "total_answered": 874,
        "total_answered_correctly": 308
      },
      {
        "seconds_passed": 130,
        "total_answered": 885,
        "total_answered_correctly": 312
      },
      {
        "seconds_passed": 135,
        "total_answered": 900,
        "total_answered_correctly": 320
      },
      {
        "seconds_passed": 140,
        "total_answered": 918,
        "total_answered_correctly": 330
      },
      {
        "seconds_passed": 145,
        "total_answered": 930,
        "total_answered_correctly": 337
      },
      {
        "seconds_passed": 150,
        "total_answered": 939,
        "total_answered_correctly": 338
      },
      {
        "seconds_passed": 155,
        "total_answered": 950,
        "total_answered_correctly": 341
      },
      {
        "seconds_passed": 160,
        "total_answered": 960,
        "total_answered_correctly": 347
      },
      {
        "seconds_passed": 165,
        "total_answered": 968,
        "total_answered_correctly": 352
      },
      {
        "seconds_passed": 170,
        "total_answered": 978,
        "total_answered_correctly": 357
      },
      {
        "seconds_passed": 175,
        "total_answered": 989,
        "total_answered_correctly": 359
      },
      {
        "seconds_passed": 180,
        "total_answered": 994,
        "total_answered_correctly": 361
      },
      {
        "seconds_passed": 185,
        "total_answered": 998,
        "total_answered_correctly": 363
      },
      {
        "seconds_passed": 190,
        "total_answered": 1004,
        "total_answered_correctly": 365
      },
      {
        "seconds_passed": 195,
        "total_answered": 1009,
        "total_answered_correctly": 368
      },
      {
        "seconds_passed": 200,
        "total_answered": 1011,
        "total_answered_correctly": 368
      }
    ]
  }
]